pybimscantools/IfcConvert.exe
pybimscantools/__init__.py
pybimscantools/coordinatelist.py
pybimscantools/coordinatemodel.py
pybimscantools/depth_rendering.py
pybimscantools/droneharmony.py
pybimscantools/exif.py
pybimscantools/helper.py
pybimscantools/ifcconvert.py
pybimscantools/isococ.py
pybimscantools/markers.py
pybimscantools/markersbackend.py
pybimscantools/pix4dcli.py
pybimscantools/pointcloud.py
pybimscantools/textcolor.py
pybimscantools/transformations.py
pybimscantools-0.1.0.post2.dist-info/LICENSE
pybimscantools-0.1.0.post2.dist-info/METADATA
pybimscantools-0.1.0.post2.dist-info/WHEEL
pybimscantools-0.1.0.post2.dist-info/top_level.txt
pybimscantools-0.1.0.post2.dist-info/RECORD
